myraf-3.1.5.dist-info/licenses/LICENSE
myrafgui/__init__.py
myrafgui/about.py
myrafgui/align.py
myrafgui/arithmetic.py
myrafgui/bin.py
myrafgui/ccdproc.py
myrafgui/combine.py
myrafgui/cosmic_cleaner.py
myrafgui/crop.py
myrafgui/display.py
myrafgui/functions.py
myrafgui/functions_old.py
myrafgui/header.py
myrafgui/header_calculator.py
myrafgui/hedit.py
myrafgui/hselect.py
myrafgui/log.py
myrafgui/main.py
myrafgui/observatories.py
myrafgui/photometry.py
myrafgui/rotate.py
myrafgui/settings.py
myrafgui/shift.py
myrafgui/statics.py
myrafgui/wcs.py
myraflib/__init__.py
myraflib/error.py
myraflib/fits.py
myraflib/fitsarray.py
myraflib/models.py
myraflib/py.typed
myraflib/sample.fits
myraflib/utils.py
myraf-3.1.5.dist-info/METADATA
myraf-3.1.5.dist-info/WHEEL
myraf-3.1.5.dist-info/entry_points.txt
myraf-3.1.5.dist-info/top_level.txt
myraf-3.1.5.dist-info/RECORD
