Metadata-Version: 2.4
Name: myraf
Version: 3.1.5
Summary: MYRaf; an astropy wrapper for astronomical photometry
Home-page: https://github.com/myrafproject/myrafproject
Author: Mohammad S.Niaei, Yücel KILIÇ
Author-email: niaei@pardus.org.tr, ykilic@iaa.es
License: GNU/GPL V3
Keywords: Fits,Photometry
Classifier: Programming Language :: Python :: 3
Classifier: Programming Language :: Python :: 3 :: Only
Classifier: Programming Language :: Python :: 3.11
Classifier: Operating System :: MacOS
Classifier: Operating System :: Microsoft :: Windows
Classifier: Operating System :: POSIX :: Linux
Requires-Python: ==3.11.*
License-File: LICENSE
Requires-Dist: astroalign
Requires-Dist: astropy
Requires-Dist: astroquery
Requires-Dist: ccdproc
Requires-Dist: matplotlib
Requires-Dist: mpl_point_clicker
Requires-Dist: numpy==1.24.4
Requires-Dist: opencv-python-headless
Requires-Dist: pandas
Requires-Dist: photutils
Requires-Dist: python_dateutil
Requires-Dist: sep
Requires-Dist: typing_extensions
Requires-Dist: scipy
Requires-Dist: ginga
Requires-Dist: PyQt5
Requires-Dist: pyqtdarktheme
Requires-Dist: tqdm
Requires-Dist: tox
Provides-Extra: testing
Requires-Dist: pytest; extra == "testing"
Requires-Dist: pytest-cov; extra == "testing"
Requires-Dist: mypy; extra == "testing"
Requires-Dist: flake8; extra == "testing"
Dynamic: license-file
